{
  "title": "Políticas",
  "body": "![Políticas](/img/uploads/accept-terms.gif \"Políticas\")\n\n<h5><a target=\"_blank\" rel=\"noopener noreferrer\" href=\"https://www.macpremier.com.br/pages/privacidade\"><span style=\"color:hsl( 0, 0%, 15% );\"><u>Política de privacidade</u></span></a></h5>\n<h5><a target=\"_blank\" rel=\"noopener noreferrer\" href=\"https://www.macpremier.com.br/pages/politica-de-cookies\"><span style=\"color:hsl( 0, 0%, 15% );\"><u>Política de Cookies</u></span></a></h5>\n<h5><a target=\"_blank\" rel=\"noopener noreferrer\" href=\"https://www.macpremier.com.br/pages/termos\"><span style=\"color:hsl( 0, 0%, 15% );\"><u>Termos de uso</u></span></a></h5>\n<h5><a target=\"_blank\" rel=\"noopener noreferrer\" href=\"https://www.macpremier.com.br/pages/trocas\"><span style=\"color:hsl( 0, 0%, 15% );\"><u>Trocas e devoluções</u></span></a></h5>",
  "meta_description": "Prezado cliente, ao navegar e realizar compras em nosso e-commerce, você concorda com as políticas descritas abaixo. Estas políticas foram criadas para garantir uma experiência de compra segura, justa e transparente para todos os nossos clientes.",
  "meta_title": "Políticas | MacPremier (Brasil)",
  "sections": [
    {
      "type": "info-bar",
      "enabled": true
    },
    {
      "type": "page-title",
      "description": "Prezado cliente, ao navegar e realizar compras em nosso e-commerce, você concorda com as políticas descritas abaixo. Estas políticas foram criadas para garantir uma experiência de compra segura, justa e transparente para todos os nossos clientes.",
      "title": "Políticas do MacPremier"
    },
    {
      "type": "extra-page",
      "enabled": true
    },
    {
      "type": "blog",
      "enabled": true
    }
  ]
}